sphinx_autoissues/__init__.py
sphinx_autoissues/issuetracker.css
sphinx_autoissues/resolvers.py
sphinx_autoissues/types.py
sphinx_autoissues/utils.py
sphinx_autoissues-0.0.1.dist-info/LICENSE
sphinx_autoissues-0.0.1.dist-info/WHEEL
sphinx_autoissues-0.0.1.dist-info/METADATA
sphinx_autoissues-0.0.1.dist-info/RECORD
