Metadata-Version: 2.1
Name: sphinx-autoissues
Version: 0.0.1
Summary: Sphinx integration with different issuetrackers
Home-page: https://sphinx-autoissues.git-pull.com
License: BSD
Keywords: sphinx,docutils,issues,pull requests
Author: Tony Narlock
Author-email: tony@git-pull.com
Requires-Python: >=3.7,<4.0
Classifier: Development Status :: 5 - Production/Stable
Classifier: Environment :: Web Environment
Classifier: Intended Audience :: Developers
Classifier: License :: OSI Approved :: BSD License
Classifier: License :: Other/Proprietary License
Classifier: Programming Language :: Python
Classifier: Programming Language :: Python :: 3
Classifier: Programming Language :: Python :: 3.10
Classifier: Programming Language :: Python :: 3.7
Classifier: Programming Language :: Python :: 3.8
Classifier: Programming Language :: Python :: 3.9
Classifier: Programming Language :: Python :: Implementation :: PyPy
Classifier: Topic :: Software Development :: Internationalization
Classifier: Topic :: Software Development :: Localization
Classifier: Topic :: Utilities
Classifier: Typing :: Typed
Provides-Extra: coverage
Provides-Extra: docs
Provides-Extra: format
Provides-Extra: lint
Provides-Extra: test
Project-URL: Bug Tracker, https://github.com/tony/sphinx-autoissues/issues
Project-URL: Changes, https://github.com/tony/sphinx-autoissues/blob/master/CHANGES
Project-URL: Documentation, https://sphinx-autoissues.git-pull.com
Project-URL: Repository, https://github.com/tony/sphinx-autoissues
